moclo/kits/__init__.py
moclo/kits/ecoflex.py
moclo/kits/ecoflex.version
moclo/registry/ecoflex.json.bz2
moclo/registry/ecoflex.py
moclo_ecoflex-0.3.1.dist-info/COPYING
moclo_ecoflex-0.3.1.dist-info/METADATA
moclo_ecoflex-0.3.1.dist-info/WHEEL
moclo_ecoflex-0.3.1.dist-info/top_level.txt
moclo_ecoflex-0.3.1.dist-info/zip-safe
moclo_ecoflex-0.3.1.dist-info/RECORD
